django_conventions/__init__.py
django_conventions/conventions.py
django_conventions/introspector.py
django_conventions/urls_manager.py
django_conventions/utils.py
django_conventions/rest/__init__.py
django_conventions/rest/views.py
django_conventions-0.2.2.dist-info/METADATA
django_conventions-0.2.2.dist-info/WHEEL
django_conventions-0.2.2.dist-info/top_level.txt
django_conventions-0.2.2.dist-info/RECORD
